cuia/__init__.py
cuia/command.py
cuia/messages/__init__.py
cuia/messages/event.py
cuia/messages/message.py
cuia/program.py
cuia/renderer/__init__.py
cuia/renderer/curses.py
cuia/renderer/log.py
cuia/renderer/renderer.py
cuia/store.py
cuia-0.1.1.dist-info/LICENSE
cuia-0.1.1.dist-info/WHEEL
cuia-0.1.1.dist-info/METADATA
cuia-0.1.1.dist-info/RECORD
