Metadata-Version: 2.1
Name: cuia
Version: 0.1.1
Summary: 🧉🌿 A delightful tiny framework for building reliable text-based applications
Home-page: https://github.com/getcuia/cuia
License: MIT
Keywords: ansi,cli,command-line,console,cuia,elm-architecture,framework,functional,gui,simple,terminal-based,terminal,toolkit,tui,ui,user-interface
Author: Felipe S. S. Schneider
Author-email: schneider.felipe@posgrad.ufsc.br
Requires-Python: >=3.8,<4.0
Classifier: Development Status :: 4 - Beta
Classifier: Environment :: Console
Classifier: Intended Audience :: Developers
Classifier: License :: OSI Approved :: MIT License
Classifier: Programming Language :: Python :: 3
Classifier: Programming Language :: Python :: 3.10
Classifier: Programming Language :: Python :: 3.8
Classifier: Programming Language :: Python :: 3.9
Classifier: Topic :: Software Development :: Libraries :: Application Frameworks
Classifier: Topic :: Software Development :: Libraries :: Python Modules
Classifier: Topic :: Software Development :: User Interfaces
Classifier: Topic :: Terminals :: Terminal Emulators/X Terminals
Classifier: Topic :: Utilities
Requires-Dist: cusser (>=0.1.1,<0.2.0)
Project-URL: Repository, https://github.com/getcuia/cuia
